malparser/__init__.py
malparser/__main__.py
malparser/anime.py
malparser/base.py
malparser/mal.py
malparser/manga.py
malparser/searchresult.py
malparser-1.1.12.dist-info/LICENSE
malparser-1.1.12.dist-info/METADATA
malparser-1.1.12.dist-info/WHEEL
malparser-1.1.12.dist-info/top_level.txt
malparser-1.1.12.dist-info/RECORD
