Metadata-Version: 2.1
Name: malparser
Version: 1.1.12
Summary: Python package to access the MyAnimeList Anime
Home-page: https://github.com/JohnDoee/malparser
Author: Anders Jensen
Author-email: johndoee+malparser@tidalstream.org
License: MIT
Platform: UNKNOWN
Classifier: Development Status :: 5 - Production/Stable
Classifier: Intended Audience :: Developers
Classifier: License :: OSI Approved :: MIT License
Classifier: Operating System :: OS Independent
Classifier: Programming Language :: Python
Classifier: Topic :: Database :: Front-Ends
Classifier: Topic :: Software Development :: Libraries :: Python Modules
License-File: LICENSE
Requires-Dist: requests
Requires-Dist: lxml
